stasma/__init__.py
stasma/const.py
stasma/graphics.py
stasma/logger.py
stasma/units.py
stasma/utils.py
stasma/base/__init__.py
stasma/base/body.py
stasma/base/spot.py
stasma/base/star.py
stasma/base/system.py
stasma/binary_system/__init__.py
stasma/binary_system/build.py
stasma/binary_system/orbit.py
stasma/binary_system/plot.py
stasma/binary_system/static.py
stasma/binary_system/system.py
stasma/conf/__init__.py
stasma/conf/config.py
stasma/conf/logging.json
stasma/conf/stasma_conf.ini
stasma/single_system/__init__.py
stasma/single_system/build.py
stasma/single_system/plot.py
stasma/single_system/static.py
stasma/single_system/system.py
stasma-0.1.2.dist-info/METADATA
stasma-0.1.2.dist-info/RECORD
stasma-0.1.2.dist-info/WHEEL
stasma-0.1.2.dist-info/entry_points.txt
stasma-0.1.2.dist-info/top_level.txt
