Metadata-Version: 2.1
Name: stasma
Version: 0.1.2
Summary: Stellar surface maker
Home-page: https://github.com/mikecokina/stasma.git
Author: Michal Cokina, Miroslav Fedurco
Author-email: UNKNOWN
License: UNKNOWN
Keywords: eclipsing binaries astronomy analysis physic
Platform: UNKNOWN
Classifier: Development Status :: 4 - Beta
Classifier: Intended Audience :: Developers
Classifier: Topic :: Scientific/Engineering :: Astronomy
Classifier: Programming Language :: Python :: 3.6
Requires-Dist: astropy (==2.0.2)
Requires-Dist: cycler (==0.10.0)
Requires-Dist: matplotlib (==2.1.0)
Requires-Dist: numpy (==1.13.3)
Requires-Dist: pandas (==0.23.0)
Requires-Dist: py (==1.4.34)
Requires-Dist: pyparsing (==2.2.0)
Requires-Dist: pytest (==3.2.3)
Requires-Dist: python-dateutil (==2.6.1)
Requires-Dist: pytz (==2017.2)
Requires-Dist: scipy (==1.0.0)
Requires-Dist: six (==1.11.0)
Provides-Extra: dev
